pylotree.py
pylotree-0.2.0.dist-info/LICENSE
pylotree-0.2.0.dist-info/METADATA
pylotree-0.2.0.dist-info/WHEEL
pylotree-0.2.0.dist-info/top_level.txt
pylotree-0.2.0.dist-info/RECORD
